pylhb/__init__.py
pylhb/myconfig.py
pylhb/myjson.py
pylhb/mylog.py
pylhb/myodbc.py
pylhb/mysqlite.py
pylhb-0.2.3.dist-info/WHEEL
pylhb-0.2.3.dist-info/entry_points.txt
pylhb-0.2.3.dist-info/METADATA
pylhb-0.2.3.dist-info/RECORD
