Metadata-Version: 2.3
Name: pylhb
Version: 0.2.3
Summary: Mr.Lee's Helpers
License: Non-Commercial Use License
Requires-Dist: pyodbc>=5.3.0
Requires-Python: >=3.12
